KMC/client/configuration.py
KMC/client/input_grabbing.py
KMC/client/kmc.py
KMC/client/communication/base.py
KMC/client/communication/debug.py
KMC/client/communication/tcpip.py
KMC/client/communication/transmitter_management.py
KMC/communication/base.py
KMC/communication/control_items.py
KMC/communication/debug.py
KMC/communication/tcpip.py
KMC/communication/asynctcpcs/client.py
KMC/communication/asynctcpcs/server.py
KMC/communication/asynctcpcs/transferutils.py
KMC/configuration/base.py
KMC/os_api/infinite_mouse_manager.py
KMC/os_api/input_grabbing.py
KMC/os_api/input_items.py
KMC/os_api/input_processing.py
KMC/server/configuration.py
KMC/server/kmc.py
KMC/server/communication/base.py
KMC/server/communication/receiver_management.py
KMC/server/communication/tcpip.py
kmc-1.0.1.dist-info/METADATA
kmc-1.0.1.dist-info/WHEEL
kmc-1.0.1.dist-info/entry_points.txt
kmc-1.0.1.dist-info/RECORD
